cobaltuoft/__init__.py
cobaltuoft/cobalt.py
cobaltuoft/datasets.py
cobaltuoft/endpoints.py
cobaltuoft/response.py
cobaltuoft/helpers/__init__.py
cobaltuoft/helpers/scrapers/__init__.py
cobaltuoft/helpers/scrapers/active_apis.py
cobaltuoft/helpers/scrapers/filter_keys.py
cobaltuoft-0.1.0.dist-info/DESCRIPTION.rst
cobaltuoft-0.1.0.dist-info/METADATA
cobaltuoft-0.1.0.dist-info/RECORD
cobaltuoft-0.1.0.dist-info/WHEEL
cobaltuoft-0.1.0.dist-info/metadata.json
cobaltuoft-0.1.0.dist-info/top_level.txt
