Metadata-Version: 2.0
Name: cobaltuoft
Version: 0.1.0
Summary: A Python Cobalt library.
Home-page: https://github.com/kshvmdn/cobalt-uoft-python
Author: Kashav Madan
Author-email: kshvmdn@gmail.com
License: MIT
Keywords: cobalt,uoft,university of toronto,api wrapper,open data
Platform: UNKNOWN
Classifier: Development Status :: 3 - Alpha
Classifier: Programming Language :: Python :: 3
Classifier: Programming Language :: Python :: 3.3
Classifier: Programming Language :: Python :: 3.4
Classifier: Programming Language :: Python :: 3.5
Requires-Dist: bs4
Requires-Dist: requests
